README.rst
setup.py
pygrowthmodels/__init__.py
pygrowthmodels/blumberg.py
pygrowthmodels/brody.py
pygrowthmodels/chapman_richards.py
pygrowthmodels/gompertz.py
pygrowthmodels/janoschek.py
pygrowthmodels/logistic.py
pygrowthmodels/mitcherlich.py
pygrowthmodels/mmf.py
pygrowthmodels/monomolecular.py
pygrowthmodels/negative_exponential.py
pygrowthmodels/richard.py
pygrowthmodels/rosso.py
pygrowthmodels/schnute.py
pygrowthmodels/stannard.py
pygrowthmodels/vonbertalanffy.py
pygrowthmodels/weibull.py
pygrowthmodels.egg-info/PKG-INFO
pygrowthmodels.egg-info/SOURCES.txt
pygrowthmodels.egg-info/dependency_links.txt
pygrowthmodels.egg-info/top_level.txt
tests/__init__.py
tests/test_blumberg.py
tests/test_brody.py
tests/test_chapman_richards.py
tests/test_gompertz.py
tests/test_janoschek.py
tests/test_logistic.py
tests/test_mitcherlich.py
tests/test_mmf.py
tests/test_monomolecular.py
tests/test_negative_exponential.py
tests/test_richard.py
tests/test_rosso.py
tests/test_schnute.py
tests/test_stannard.py
tests/test_vonbertalanffy.py
tests/test_weibull.py