Metadata-Version: 1.1
Name: pygrowthmodels
Version: 0.0.3
Summary: A compilation of nonlinear growth models
Home-page: https://github.com/drodriguezperez/pygrowthmodels.git
Author: Daniel Rodríguez Pérez
Author-email: daniel.rodriguez.perez@gmail.com
License: GPL-3
Platform: UNKNOWN
Classifier: Programming Language :: Python :: 3
Classifier: Programming Language :: Python :: 3.3
Classifier: Programming Language :: Python :: 3.4
Classifier: Programming Language :: Python :: 3.5
Classifier: Programming Language :: Python :: 3.6
